{
	"description": "项目配置文件。",
	"setting": {
		"urlCheck": true,
		"es6": true,
		"postcss": true,
		"minified": true,
		"newFeature": true
	},
	"compileType": "miniprogram",
	"libVersion": "1.7.2",
	"appid": "wx2e75787e968b7262",
	"projectname": "llr-dev",
	"condition": {
		"search": {
			"current": -1,
			"list": []
		},
		"conversation": {
			"current": -1,
			"list": []
		},
		"game": {
			"current": -1,
			"list": []
		},
		"miniprogram": {
			"current": 1,
			"list": [
				{
					"id": -1,
					"name": "s's'p首页",
					"pathName": "ssp/index/index",
					"query": ""
				},
				{
					"id": -1,
					"name": "ssp门店列表",
					"pathName": "ssp/company-list/company-list",
					"query": ""
				}
			]
		}
	}
}